setup.py
savimonty_distributions/Binomialdistribution.py
savimonty_distributions/Gaussiandistribution.py
savimonty_distributions/Generaldistribution.py
savimonty_distributions/__init__.py
savimonty_distributions.egg-info/PKG-INFO
savimonty_distributions.egg-info/SOURCES.txt
savimonty_distributions.egg-info/dependency_links.txt
savimonty_distributions.egg-info/not-zip-safe
savimonty_distributions.egg-info/top_level.txt