Metadata-Version: 1.0
Name: savimonty-distributions
Version: 0.1
Summary: Probability Distributions
Home-page: UNKNOWN
Author: UNKNOWN
Author-email: UNKNOWN
License: UNKNOWN
Platform: UNKNOWN
